{"nodes": [{"id": "nix_darwin_home_root", "label": "home.nix (home-manager user config)", "file_type": "code", "source_file": "home.nix", "source_location": null, "source_url": null, "captured_at": null, "author": null, "contributor": null}, {"id": "nix_darwin_home_proton_pass_agent", "label": "launchd agent proton-pass-agent (ssh-agent)", "file_type": "rationale", "source_file": "home.nix", "source_location": "line 87", "source_url": null, "captured_at": null, "author": null, "contributor": null}, {"id": "nix_darwin_home_proton_pass_cli", "label": "Proton Pass CLI install (pnpm activation)", "file_type": "rationale", "source_file": "home.nix", "source_location": "line 46", "source_url": null, "captured_at": null, "author": null, "contributor": null}, {"id": "nix_darwin_home_atuin_daemon", "label": "launchd agent atuin-daemon", "file_type": "rationale", "source_file": "home.nix", "source_location": "line 168", "source_url": null, "captured_at": null, "author": null, "contributor": null}, {"id": "nix_darwin_home_git_config", "label": "git configuration (delta, credential helpers)", "file_type": "code", "source_file": "home.nix", "source_location": "line 104", "source_url": null, "captured_at": null, "author": null, "contributor": null}, {"id": "nix_darwin_home_wezterm_config", "label": "wezterm.lua config", "file_type": "code", "source_file": "home.nix", "source_location": "line 206", "source_url": null, "captured_at": null, "author": null, "contributor": null}, {"id": "nix_darwin_home_alias_files", "label": "rendered shell alias files (~/.config/sh/aliases{,.nu})", "file_type": "code", "source_file": "home.nix", "source_location": "line 62", "source_url": null, "captured_at": null, "author": null, "contributor": null}, {"id": "nix_darwin_home_chezmoi_division", "label": "nix/chezmoi division of labor", "file_type": "rationale", "source_file": "home.nix", "source_location": "line 13", "source_url": null, "captured_at": null, "author": null, "contributor": null}], "edges": [{"source": "nix_darwin_home_proton_pass_agent", "target": "nix_darwin_home_proton_pass_cli", "relation": "references", "confidence": "EXTRACTED", "confidence_score": 1.0, "source_file": "home.nix", "source_location": "line 79", "weight": 1.0}, {"source": "nix_darwin_home_proton_pass_agent", "target": "nix_darwin_shared_toml_ssh_auth_sock", "relation": "shares_data_with", "confidence": "EXTRACTED", "confidence_score": 1.0, "source_file": "home.nix", "source_location": "line 84", "weight": 1.0}, {"source": "nix_darwin_home_alias_files", "target": "nix_darwin_shared_toml_aliases", "relation": "shares_data_with", "confidence": "EXTRACTED", "confidence_score": 1.0, "source_file": "home.nix", "source_location": "line 64", "weight": 1.0}, {"source": "nix_darwin_home_root", "target": "nix_darwin_shared_toml", "relation": "references", "confidence": "EXTRACTED", "confidence_score": 1.0, "source_file": "home.nix", "source_location": "line 10", "weight": 1.0}, {"source": "nix_darwin_home_chezmoi_division", "target": "nix_darwin_home_alias_files", "relation": "rationale_for", "confidence": "EXTRACTED", "confidence_score": 1.0, "source_file": "home.nix", "source_location": "line 13", "weight": 1.0}, {"source": "nix_darwin_home_proton_pass_agent", "target": "nix_darwin_home_atuin_daemon", "relation": "semantically_similar_to", "confidence": "INFERRED", "confidence_score": 0.85, "source_file": "home.nix", "source_location": "line 158", "weight": 1.0}], "hyperedges": [{"id": "proton_pass_ssh_agent_flow", "label": "Proton Pass CLI ssh-agent: install, launchd agent, socket env, system agent disabled", "nodes": ["nix_darwin_home_proton_pass_cli", "nix_darwin_home_proton_pass_agent", "nix_darwin_shared_toml_ssh_auth_sock", "nix_darwin_configuration_disable_openssh_agent"], "relation": "participate_in", "confidence": "EXTRACTED", "confidence_score": 1.0, "source_file": "home.nix"}]}